<annotation>
	<folder>n01491361</folder>
	<filename>n01491361_8587</filename>
	<source>
		<database>ILSVRC_2012</database>
	</source>
	<size>
		<width>500</width>
		<height>333</height>
		<depth>3</depth>
	</size>
	<segmented>0</segmented>
	<object>
		<name>n01491361</name>
		<pose>Unspecified</pose>
		<truncated>0</truncated>
		<difficult>0</difficult>
		<bndbox>
			<xmin>151</xmin>
			<ymin>52</ymin>
			<xmax>499</xmax>
			<ymax>223</ymax>
		</bndbox>
	</object>
	<object>
		<name>n01491361</name>
		<pose>Unspecified</pose>
		<truncated>0</truncated>
		<difficult>0</difficult>
		<bndbox>
			<xmin>312</xmin>
			<ymin>201</ymin>
			<xmax>440</xmax>
			<ymax>281</ymax>
		</bndbox>
	</object>
</annotation>